{
  "name": "Geography-58d372dd-b829-4a56-ab9b-7254792b8d12",
  "mode": "import",
  "source": {
    "type": "m",
    "expression": [
      "let",
      "    Source = Access.Database(File.Contents(\"C:\\Users\\owend\\Documents\\ContosoSalesV31_64bit.accdb\")),",
      "    _DimGeography = Source{[Schema=\"\",Item=\"DimGeography\"]}[Data],",
      "    #\"Removed Columns\" = Table.RemoveColumns(_DimGeography,{\"ETLLoadID\", \"LoadDate\", \"UpdateDate\"})",
      "in",
      "    #\"Removed Columns\""
    ]
  }
}